balatrobot/__init__.py
balatrobot/__main__.py
balatrobot/cli.py
balatrobot/config.py
balatrobot/manager.py
balatrobot/platforms/__init__.py
balatrobot/platforms/base.py
balatrobot/platforms/macos.py
balatrobot/platforms/native.py
balatrobot/platforms/windows.py
balatrobot-1.3.4.dist-info/METADATA
balatrobot-1.3.4.dist-info/WHEEL
balatrobot-1.3.4.dist-info/entry_points.txt
balatrobot-1.3.4.dist-info/licenses/LICENSE
balatrobot-1.3.4.dist-info/RECORD
