Metadata-Version: 2.4
Name: balatrobot
Version: 1.3.4
Summary: API for developing Balatro bots
Project-URL: Homepage, https://github.com/coder/balatrobot
Project-URL: Issues, https://github.com/coder/balatrobot/issues
Project-URL: Repository, https://github.com/coder/balatrobot
Project-URL: Changelog, https://github.com/coder/balatrobot/blob/main/CHANGELOG.md
Author: stirby, giewev, besteon, phughesion
Author-email: S1M0N38 <bertolottosimone@gmail.com>
License-File: LICENSE
Classifier: Framework :: Pytest
Classifier: Intended Audience :: Developers
Classifier: License :: OSI Approved :: MIT License
Classifier: Programming Language :: Python :: 3.13
Requires-Python: >=3.13
Requires-Dist: httpx>=0.28.1
